Workbook

Sheet file_analysis_results_20251229_
A1: filename | B1: projectname | C1: country | D1: version | E1: date | F1: time | G1: crc | H1: release | I1: file_size | J1: full_path
A2: KB05113_DE_1.0.0.240607_release.bin | B2: KB05113 | C2: DE | D2: 1.0.0 | E2: 240607 | F2: =DATE(2000+LEFT(E2,2), MID(E2,3,2), RIGHT(E2,2)) -> 45450 | H2: release | I2: 80368 | J2: D:\Data\Document\ProductsLibrary\C线产品资料库\KB05113 自研软件\1.0.0\KB05113_DE_1.0.0.240607_release\KB05113_DE_1.0.0.240607_release.bin
A3: KB05113_DE_1.0.0.240607_release_Encrypt.bin | B3: KB05113 | C3: DE | D3: 1.0.0 | E3: 240607 | F3: =DATE(2000+LEFT(E3,2), MID(E3,3,2), RIGHT(E3,2)) -> 45450 | H3: release | I3: 80392 | J3: D:\Data\Document\ProductsLibrary\C线产品资料库\KB05113 自研软件\1.0.0\KB05113_DE_1.0.0.240607_release\KB05113_DE_1.0.0.240607_release_Encrypt.bin
A4: KB05113_UK_1.0.0.240607_release.bin | B4: KB05113 | C4: UK | D4: 1.0.0 | E4: 240607 | F4: =DATE(2000+LEFT(E4,2), MID(E4,3,2), RIGHT(E4,2)) -> 45450 | H4: release | I4: 80368 | J4: D:\Data\Document\ProductsLibrary\C线产品资料库\KB05113 自研软件\1.0.0\KB05113_UK_1.0.0.240607_release\KB05113_UK_1.0.0.240607_release.bin
A5: KB05113_UK_1.0.0.240607_release_Encrypt.bin | B5: KB05113 | C5: UK | D5: 1.0.0 | E5: 240607 | F5: =DATE(2000+LEFT(E5,2), MID(E5,3,2), RIGHT(E5,2)) -> 45450 | H5: release | I5: 80392 | J5: D:\Data\Document\ProductsLibrary\C线产品资料库\KB05113 自研软件\1.0.0\KB05113_UK_1.0.0.240607_release\KB05113_UK_1.0.0.240607_release_Encrypt.bin
A6: KB05113_US_1.0.0.240607_release.bin | B6: KB05113 | C6: US | D6: 1.0.0 | E6: 240607 | F6: =DATE(2000+LEFT(E6,2), MID(E6,3,2), RIGHT(E6,2)) -> 45450 | H6: release | I6: 80368 | J6: D:\Data\Document\ProductsLibrary\C线产品资料库\KB05113 自研软件\1.0.0\KB05113_US_1.0.0.240607_release\KB05113_US_1.0.0.240607_release.bin
A7: KB05113_US_1.0.0.240607_release_Encrypt.bin | B7: KB05113 | C7: US | D7: 1.0.0 | E7: 240607 | F7: =DATE(2000+LEFT(E7,2), MID(E7,3,2), RIGHT(E7,2)) -> 45450 | H7: release | I7: 80392 | J7: D:\Data\Document\ProductsLibrary\C线产品资料库\KB05113 自研软件\1.0.0\KB05113_US_1.0.0.240607_release\KB05113_US_1.0.0.240607_release_Encrypt.bin
A8: KB02027_DE_2.2.2.240717_release.bin | B8: KB02027 | C8: DE | D8: 2.2.2 | E8: 240717 | F8: =DATE(2000+LEFT(E8,2), MID(E8,3,2), RIGHT(E8,2)) -> 45490 | H8: release | I8: 82272 | J8: D:\Data\Document\ProductsLibrary\C线产品资料库\KB02027\固件释放\KB02027_DE_2.2.2.240717_release.bin
A9: KB02027_UK_2.2.2.240717_release.bin | B9: KB02027 | C9: UK | D9: 2.2.2 | E9: 240717 | F9: =DATE(2000+LEFT(E9,2), MID(E9,3,2), RIGHT(E9,2)) -> 45490 | H9: release | I9: 82272 | J9: D:\Data\Document\ProductsLibrary\C线产品资料库\KB02027\固件释放\KB02027_UK_2.2.2.240717_release.bin
A10: KB02027_US_2.2.2.240717_release.bin | B10: KB02027 | C10: US | D10: 2.2.2 | E10: 240717 | F10: =DATE(2000+LEFT(E10,2), MID(E10,3,2), RIGHT(E10,2)) -> 45490 | H10: release | I10: 82268 | J10: D:\Data\Document\ProductsLibrary\C线产品资料库\KB02027\固件释放\KB02027_US_2.2.2.240717_release.bin
A11: KB02027_DE_2.2.2.240717_release.bin | B11: KB02027 | C11: DE | D11: 2.2.2 | E11: 240717 | F11: =DATE(2000+LEFT(E11,2), MID(E11,3,2), RIGHT(E11,2)) -> 45490 | H11: release | I11: 82272 | J11: D:\Data\Document\ProductsLibrary\C线产品资料库\KB02027_black\固件释放\KB02027_DE_2.2.2.240717_release.bin
A12: KB02027_UK_2.2.2.240717_release.bin | B12: KB02027 | C12: UK | D12: 2.2.2 | E12: 240717 | F12: =DATE(2000+LEFT(E12,2), MID(E12,3,2), RIGHT(E12,2)) -> 45490 | H12: release | I12: 82272 | J12: D:\Data\Document\ProductsLibrary\C线产品资料库\KB02027_black\固件释放\KB02027_UK_2.2.2.240717_release.bin
A13: KB09119_11_DE_0.0.18.240725_release.bin | B13: KB09119_11 | C13: DE | D13: 0.0.18 | E13: 240725 | F13: =DATE(2000+LEFT(E13,2), MID(E13,3,2), RIGHT(E13,2)) -> 45498 | H13: release | I13: 80144 | J13: D:\Data\Document\ProductsLibrary\C线产品资料库\KB09119_11_black\固件释放\KB09119_11_DE_0.0.18.240725_release.bin
... A15: KB09119_11_US_0.0.18.240725_release.bin | B15: KB09119_11 | C15: US | D15: 0.0.18 | E15: 240725 | F15: =DATE(2000+LEFT(E15,2), MID(E15,3,2), RIGHT(E15,2)) -> 45498 | H15: release | I15: 80128 | J15: D:\Data\Document\ProductsLibrary\C线产品资料库\KB09119_11_black\固件释放\KB09119_11_US_0.0.18.240725_release.bin
A16: KB04111_DE_0.0.10.240726_beta.bin | B16: KB04111 | C16: DE | D16: 0.0.10 | E16: 240726 | H16: beta | I16: 80304 | J16: D:\Data\Document\ProductsLibrary\C线产品资料库\KB04111\固件\KB04111_DE_0.0.10.240726_release\KB04111_DE_0.0.10.240726_beta.bin
A17: KB04111_UK_0.0.10.240726_beta.bin | B17: KB04111 | C17: UK | D17: 0.0.10 | E17: 240726 | H17: beta | I17: 80304 | J17: D:\Data\Document\ProductsLibrary\C线产品资料库\KB04111\固件\KB04111_UK_0.0.10.240726_release\KB04111_UK_0.0.10.240726_beta.bin
A18: KB04111_US_0.0.10.240726_beta.bin | B18: KB04111 | C18: US | D18: 0.0.10 | E18: 240726 | H18: beta | I18: 80144 | J18: D:\Data\Document\ProductsLibrary\C线产品资料库\KB04111\固件\KB04111_US_0.0.10.240726_release\KB04111_US_0.0.10.240726_beta.bin
A19: KB04122_DE_0.0.4.240906_beta.bin | B19: KB04122 | C19: DE | D19: 0.0.4 | E19: 240906 | H19: beta | I19: 80084 | J19: D:\Data\Document\ProductsLibrary\C线产品资料库\KB04122\固件\beta\KB04122_0.0.4.240906_beta\DE\KB04122_DE_0.0.4.240906_beta.bin
A20: KB04122_JP_0.0.4.240906_beta.bin | B20: KB04122 | C20: JP | D20: 0.0.4 | E20: 240906 | H20: beta | I20: 79932 | J20: D:\Data\Document\ProductsLibrary\C线产品资料库\KB04122\固件\beta\KB04122_0.0.4.240906_beta\JP\KB04122_JP_0.0.4.240906_beta.bin
A21: KB04122_UK_0.0.4.240906_beta.bin | B21: KB04122 | C21: UK | D21: 0.0.4 | E21: 240906 | H21: beta | I21: 80084 | J21: D:\Data\Document\ProductsLibrary\C线产品资料库\KB04122\固件\beta\KB04122_0.0.4.240906_beta\UK\KB04122_UK_0.0.4.240906_beta.bin
A22: KB04122_US_0.0.4.240906_beta.bin | B22: KB04122 | C22: US | D22: 0.0.4 | E22: 240906 | H22: beta | I22: 79924 | J22: D:\Data\Document\ProductsLibrary\C线产品资料库\KB04122\固件\beta\KB04122_0.0.4.240906_beta\US\KB04122_US_0.0.4.240906_beta.bin
A23: KB04112_DE_0.0.1.240909_beta.bin | B23: KB04112 | C23: DE | D23: 0.0.1 | E23: 240909 | H23: beta | I23: 80384 | J23: D:\Data\Document\ProductsLibrary\C线产品资料库\KB04112_gray\固件\beta\DE\KB04112_DE_0.0.1.240909_beta.bin
A24: KB04112_UK_0.0.1.240909_beta.bin | B24: KB04112 | C24: UK | D24: 0.0.1 | E24: 240909 | H24: beta | I24: 80384 | J24: D:\Data\Document\ProductsLibrary\C线产品资料库\KB04112_gray\固件\beta\UK\KB04112_UK_0.0.1.240909_beta.bin
A25: KB04112_US_0.0.1.240909_beta.bin | B25: KB04112 | C25: US | D25: 0.0.1 | E25: 240909 | H25: beta | I25: 80224 | J25: D:\Data\Document\ProductsLibrary\C线产品资料库\KB04112_gray\固件\beta\US\KB04112_US_0.0.1.240909_beta.bin
A26: KB02028_DE_0.2.9.240911_beta.bin | B26: KB02028 | C26: DE | D26: 0.2.9 | E26: 240911 | H26: beta | I26: 83804 | J26: D:\Data\Document\ProductsLibrary\C线产品资料库\KB02028\beta\DE\KB02028_DE_0.2.9.240911_beta.bin
A27: KB02028_UK_0.2.9.240911_beta.bin | B27: KB02028 | C27: UK | D27: 0.2.9 | E27: 240911 | H27: beta | I27: 83700 | J27: D:\Data\Document\ProductsLibrary\C线产品资料库\KB02028\beta\UK\KB02028_UK_0.2.9.240911_beta.bin
A28: KB02028_US_0.2.9.240911_beta.bin | B28: KB02028 | C28: US | D28: 0.2.9 | E28: 240911 | H28: beta | I28: 83532 | J28: D:\Data\Document\ProductsLibrary\C线产品资料库\KB02028\beta\US\KB02028_US_0.2.9.240911_beta.bin
A29: KB06101_DE_0.2.18.240911_release.bin | B29: KB06101 | C29: DE | D29: 0.2.18 | E29: 240911 | F29: =DATE(2000+LEFT(E29,2), MID(E29,3,2), RIGHT(E29,2)) -> 45546 | H29: release | I29: 77020 | J29: D:\Data\Document\ProductsLibrary\C线产品资料库\KB06101\量产固件\KB06101_0.2.18.240911_release\DE\KB06101_DE_0.2.18.240911_release.bin
A30: KB06101_DE_0.2.18.240911_release_Encrypt.bin | B30: KB06101 | C30: DE | D30: 0.2.18 | E30: 240911 | F30: =DATE(2000+LEFT(E30,2), MID(E30,3,2), RIGHT(E30,2)) -> 45546 | H30: release | I30: 77040 | J30: D:\Data\Document\ProductsLibrary\C线产品资料库\KB06101\量产固件\KB06101_0.2.18.240911_release\DE\KB06101_DE_0.2.18.240911_release_Encrypt.bin
A31: KB06101_UK_0.2.18.240911_release.bin | B31: KB06101 | C31: UK | D31: 0.2.18 | E31: 240911 | F31: =DATE(2000+LEFT(E31,2), MID(E31,3,2), RIGHT(E31,2)) -> 45546 | H31: release | I31: 76940 | J31: D:\Data\Document\ProductsLibrary\C线产品资料库\KB06101\量产固件\KB06101_0.2.18.240911_release\UK\KB06101_UK_0.2.18.240911_release.bin
A32: KB06101_UK_0.2.18.240911_release_Encrypt.bin | B32: KB06101 | C32: UK | D32: 0.2.18 | E32: 240911 | F32: =DATE(2000+LEFT(E32,2), MID(E32,3,2), RIGHT(E32,2)) -> 45546 | H32: release | I32: 76960 | J32: D:\Data\Document\ProductsLibrary\C线产品资料库\KB06101\量产固件\KB06101_0.2.18.240911_release\UK\KB06101_UK_0.2.18.240911_release_Encrypt.bin
A33: KB06101_US_0.2.18.240911_release.bin | B33: KB06101 | C33: US | D33: 0.2.18 | E33: 240911 | F33: =DATE(2000+LEFT(E33,2), MID(E33,3,2), RIGHT(E33,2)) -> 45546 | H33: release | I33: 76772 | J33: D:\Data\Document\ProductsLibrary\C线产品资料库\KB06101\量产固件\KB06101_0.2.18.240911_release\US\KB06101_US_0.2.18.240911_release.bin
A34: KB06101_US_0.2.18.240911_release_Encrypt.bin | B34: KB06101 | C34: US | D34: 0.2.18 | E34: 240911 | F34: =DATE(2000+LEFT(E34,2), MID(E34,3,2), RIGHT(E34,2)) -> 45546 | H34: release | I34: 76792 | J34: D:\Data\Document\ProductsLibrary\C线产品资料库\KB06101\量产固件\KB06101_0.2.18.240911_release\US\KB06101_US_0.2.18.240911_release_Encrypt.bin
A35: KB04112_DE_0.0.2.240912_release.bin | B35: KB04112 | C35: DE | D35: 0.0.2 | E35: 240912 | F35: =DATE(2000+LEFT(E35,2), MID(E35,3,2), RIGHT(E35,2)) -> 45547 | H35: release | I35: 81404 | J35: D:\Data\Document\ProductsLibrary\C线产品资料库\KB04112_gray\固件\release\KB04112_0.0.2.240912_release\DE\KB04112_DE_0.0.2.240912_release.bin
A36: KB04112_UK_0.0.2.240912_release.bin | B36: KB04112 | C36: UK | D36: 0.0.2 | E36: 240912 | F36: =DATE(2000+LEFT(E36,2), MID(E36,3,2), RIGHT(E36,2)) -> 45547 | H36: release | I36: 81408 | J36: D:\Data\Document\ProductsLibrary\C线产品资料库\KB04112_gray\固件\release\KB04112_0.0.2.240912_release\UK\KB04112_UK_0.0.2.240912_release.bin
A37: KB04112_US_0.0.2.240912_release.bin | B37: KB04112 | C37: US | D37: 0.0.2 | E37: 240912 | F37: =DATE(2000+LEFT(E37,2), MID(E37,3,2), RIGHT(E37,2)) -> 45547 | H37: release | I37: 81236 | J37: D:\Data\Document\ProductsLibrary\C线产品资料库\KB04112_gray\固件\release\KB04112_0.0.2.240912_release\US\KB04112_US_0.0.2.240912_release.bin
A38: KB05114_ALL_1.0.5.240918_release.bin | B38: KB05114 | C38: ALL | D38: 1.0.5 | E38: 240918 | F38: =DATE(2000+LEFT(E38,2), MID(E38,3,2), RIGHT(E38,2)) -> 45553 | H38: release | I38: 81320 | J38: D:\Data\Document\ProductsLibrary\C线产品资料库\KB05114\固件释放\0918-release\KB05114_ALL_1.0.5.240918_release.bin
A39: KB01105_DE_0.0.4.240924_beta.bin | B39: KB01105 | C39: DE | D39: 0.0.4 | E39: 240924 | H39: beta | I39: 81732 | J39: D:\Data\Document\ProductsLibrary\C线产品资料库\KB01105\固件\beta\KB01105_0.0.4.240924_beta\DE\KB01105_DE_0.0.4.240924_beta.bin
A40: KB01105_UK_0.0.4.240924_beta.bin | B40: KB01105 | C40: UK | D40: 0.0.4 | E40: 240924 | H40: beta | I40: 81644 | J40: D:\Data\Document\ProductsLibrary\C线产品资料库\KB01105\固件\beta\KB01105_0.0.4.240924_beta\UK\KB01105_UK_0.0.4.240924_beta.bin
A41: KB01105_US_0.0.4.240924_beta.bin | B41: KB01105 | C41: US | D41: 0.0.4 | E41: 240924 | H41: beta | I41: 81464 | J41: D:\Data\Document\ProductsLibrary\C线产品资料库\KB01105\固件\beta\KB01105_0.0.4.240924_beta\US\KB01105_US_0.0.4.240924_beta.bin
A42: KB06101_DE_0.2.20.240925_beta.bin | B42: KB06101 | C42: DE | D42: 0.2.20 | E42: 240925 | H42: beta | I42: 75916 | J42: D:\Data\Document\ProductsLibrary\C线产品资料库\KB06101\beta固件\KB06101_0.2.20.240925_beta\DE\KB06101_DE_0.2.20.240925_beta.bin
A43: KB06101_UK_0.2.20.240925_beta.bin | B43: KB06101 | C43: UK | D43: 0.2.20 | E43: 240925 | H43: beta | I43: 75840 | J43: D:\Data\Document\ProductsLibrary\C线产品资料库\KB06101\beta固件\KB06101_0.2.20.240925_beta\UK\KB06101_UK_0.2.20.240925_beta.bin
A44: KB06101_US_0.2.20.240925_beta.bin | B44: KB06101 | C44: US | D44: 0.2.20 | E44: 240925 | H44: beta | I44: 75672 | J44: D:\Data\Document\ProductsLibrary\C线产品资料库\KB06101\beta固件\KB06101_0.2.20.240925_beta\US\KB06101_US_0.2.20.240925_beta.bin
A45: KB06101_DE_0.2.20.240926_beta.bin | B45: KB06101 | C45: DE | D45: 0.2.20 | E45: 240926 | H45: beta | I45: 75792 | J45: D:\Data\Document\ProductsLibrary\C线产品资料库\KB06101\beta固件\KB06101_0.2.20.240926_beta\DE\KB06101_DE_0.2.20.240926_beta.bin
A46: KB06101_UK_0.2.20.240926_beta.bin | B46: KB06101 | C46: UK | D46: 0.2.20 | E46: 240926 | H46: beta | I46: 75708 | J46: D:\Data\Document\ProductsLibrary\C线产品资料库\KB06101\beta固件\KB06101_0.2.20.240926_beta\UK\KB06101_UK_0.2.20.240926_beta.bin
A47: KB06101_US_0.2.20.240926_beta.bin | B47: KB06101 | C47: US | D47: 0.2.20 | E47: 240926 | H47: beta | I47: 75548 | J47: D:\Data\Document\ProductsLibrary\C线产品资料库\KB06101\beta固件\KB06101_0.2.20.240926_beta\US\KB06101_US_0.2.20.240926_beta.bin
A48: KB06101_DE_0.2.20.240926_release.bin | B48: KB06101 | C48: DE | D48: 0.2.20 | E48: 240926 | F48: =DATE(2000+LEFT(E48,2), MID(E48,3,2), RIGHT(E48,2)) -> 45561 | H48: release | I48: 75792 | J48: D:\Data\Document\ProductsLibrary\C线产品资料库\KB06101\量产固件\KB06101_0.2.20.240926_release\DE\KB06101_DE_0.2.20.240926_release.bin
A49: KB06101_UK_0.2.20.240926_release.bin | B49: KB06101 | C49: UK | D49: 0.2.20 | E49: 240926 | F49: =DATE(2000+LEFT(E49,2), MID(E49,3,2), RIGHT(E49,2)) -> 45561 | H49: release | I49: 75708 | J49: D:\Data\Document\ProductsLibrary\C线产品资料库\KB06101\量产固件\KB06101_0.2.20.240926_release\UK\KB06101_UK_0.2.20.240926_release.bin
A50: KB06101_US_0.2.20.240926_release.bin | B50: KB06101 | C50: US | D50: 0.2.20 | E50: 240926 | F50: =DATE(2000+LEFT(E50,2), MID(E50,3,2), RIGHT(E50,2)) -> 45561 | H50: release | I50: 75548 | J50: D:\Data\Document\ProductsLibrary\C线产品资料库\KB06101\量产固件\KB06101_0.2.20.240926_release\US\KB06101_US_0.2.20.240926_release.bin
A51: KB01105_DE_0.0.5.240927_beta.bin | B51: KB01105 | C51: DE | D51: 0.0.5 | E51: 240927 | H51: beta | I51: 82880 | J51: D:\Data\Document\ProductsLibrary\C线产品资料库\KB01105\固件\beta\KB01105_0.0.5.240927_beta\DE\KB01105_DE_0.0.5.240927_beta.bin
A52: KB01105_UK_0.0.5.240927_beta.bin | B52: KB01105 | C52: UK | D52: 0.0.5 | E52: 240927 | H52: beta | I52: 82832 | J52: D:\Data\Document\ProductsLibrary\C线产品资料库\KB01105\固件\beta\KB01105_0.0.5.240927_beta\UK\KB01105_UK_0.0.5.240927_beta.bin
A53: KB01105_US_0.0.5.240927_beta.bin | B53: KB01105 | C53: US | D53: 0.0.5 | E53: 240927 | H53: beta | I53: 82624 | J53: D:\Data\Document\ProductsLibrary\C线产品资料库\KB01105\固件\beta\KB01105_0.0.5.240927_beta\US\KB01105_US_0.0.5.240927_beta.bin
A54: KB06006_DE_0.0.1.241008_beta.bin | B54: KB06006 | C54: DE | D54: 0.0.1 | E54: 241008 | H54: beta | I54: 62284 | J54: D:\Data\Document\ProductsLibrary\C线产品资料库\KB06006\固件\beta\键盘\KB06006_0.0.1.241008_beta\DE\KB06006_DE_0.0.1.241008_beta.bin
A55: KB06006_DE_0.0.1.241008_beta.bin | B55: KB06006 | C55: DE | D55: 0.0.1 | E55: 241008 | H55: beta | I55: 62284 | J55: D:\Data\Document\ProductsLibrary\C线产品资料库\KB06006\固件\beta\键盘\KB06006_0.0.1.241008_beta\KB06006_0.0.1.241008_beta\DE\KB06006_DE_0.0.1.241008_beta.bin
A56: KB06006_UK_0.0.1.241008_beta.bin | B56: KB06006 | C56: UK | D56: 0.0.1 | E56: 241008 | H56: beta | I56: 62284 | J56: D:\Data\Document\ProductsLibrary\C线产品资料库\KB06006\固件\beta\键盘\KB06006_0.0.1.241008_beta\KB06006_0.0.1.241008_beta\UK\KB06006_UK_0.0.1.241008_beta.bin
A57: KB06006_US_0.0.1.241008_beta.bin | B57: KB06006 | C57: US | D57: 0.0.1 | E57: 241008 | H57: beta | I57: 62280 | J57: D:\Data\Document\ProductsLibrary\C线产品资料库\KB06006\固件\beta\键盘\KB06006_0.0.1.241008_beta\KB06006_0.0.1.241008_beta\US\KB06006_US_0.0.1.241008_beta.bin
A58: KB06006_UK_0.0.1.241008_beta.bin | B58: KB06006 | C58: UK | D58: 0.0.1 | E58: 241008 | H58: beta | I58: 62284 | J58: D:\Data\Document\ProductsLibrary\C线产品资料库\KB06006\固件\beta\键盘\KB06006_0.0.1.241008_beta\UK\KB06006_UK_0.0.1.241008_beta.bin
A59: KB06006_US_0.0.1.241008_beta.bin | B59: KB06006 | C59: US | D59: 0.0.1 | E59: 241008 | H59: beta | I59: 62280 | J59: D:\Data\Document\ProductsLibrary\C线产品资料库\KB06006\固件\beta\键盘\KB06006_0.0.1.241008_beta\US\KB06006_US_0.0.1.241008_beta.bin
A60: MS06006_ALL_0.0.1.241014_beta.bin | B60: MS06006 | C60: ALL | D60: 0.0.1 | E60: 241014 | H60: beta | I60: 55112 | J60: D:\Data\Document\ProductsLibrary\C线产品资料库\KB06006\固件\beta\鼠标\MS06006_0.0.1.241014_beta\ALL\MS06006_ALL_0.0.1.241014_beta.bin
A61: KB06006_DE_0.0.2.241015_beta.bin | B61: KB06006 | C61: DE | D61: 0.0.2 | E61: 241015 | H61: beta | I61: 64924 | J61: D:\Data\Document\ProductsLibrary\C线产品资料库\KB06006\固件\beta\键盘\KB06006_0.0.2.241015_beta\DE\KB06006_DE_0.0.2.241015_beta.bin
A62: KB06006_UK_0.0.2.241015_beta.bin | B62: KB06006 | C62: UK | D62: 0.0.2 | E62: 241015 | H62: beta | I62: 64924 | J62: D:\Data\Document\ProductsLibrary\C线产品资料库\KB06006\固件\beta\键盘\KB06006_0.0.2.241015_beta\UK\KB06006_UK_0.0.2.241015_beta.bin
... A93: KB06007_DE_0.0.2.241118_beta.bin | B93: KB06007 | C93: DE | D93: 0.0.2 | E93: 241118 | H93: beta | I93: 67516 | J93: D:\Data\Document\ProductsLibrary\C线产品资料库\KB06007\固件\beta\KB06007_0.0.2.241118_beta\DE\KB06007_DE_0.0.2.241118_beta.bin
A94: BK2007_DE_0.11.4.241126_E98C_beta_Encrypt.bin | B94: BK2007 | C94: DE | D94: 0.11.4 | E94: 241126 | G94: E98C | H94: beta | I94: 67744 | J94: D:\Data\Document\ProductsLibrary\C线产品资料库\BK2007\beta\BK2007_0.11.4.241126_beta\DE\BK2007_DE_0.11.4.241126_E98C_beta_Encrypt.bin
A95: BK2007_DE_0.11.4.241126_EFE1_beta_Open.bin | B95: BK2007 | C95: DE | D95: 0.11.4 | E95: 241126 | G95: EFE1 | H95: beta | I95: 67724 | J95: D:\Data\Document\ProductsLibrary\C线产品资料库\BK2007\beta\BK2007_0.11.4.241126_beta\DE\BK2007_DE_0.11.4.241126_EFE1_beta_Open.bin
A96: BK2007_UK_0.11.4.241126_E9A5_beta_Encrypt.bin | B96: BK2007 | C96: UK | D96: 0.11.4 | E96: 241126 | G96: E9A5 | H96: beta | I96: 67744 | J96: D:\Data\Document\ProductsLibrary\C线产品资料库\BK2007\beta\BK2007_0.11.4.241126_beta\UK\BK2007_UK_0.11.4.241126_E9A5_beta_Encrypt.bin
A97: BK2007_UK_0.11.4.241126_EFFA_beta_Open.bin | B97: BK2007 | C97: UK | D97: 0.11.4 | E97: 241126 | G97: EFFA | H97: beta | I97: 67724 | J97: D:\Data\Document\ProductsLibrary\C线产品资料库\BK2007\beta\BK2007_0.11.4.241126_beta\UK\BK2007_UK_0.11.4.241126_EFFA_beta_Open.bin
A98: BK2007_US_0.11.4.241126_E8E1_beta_Encrypt.bin | B98: BK2007 | C98: US | D98: 0.11.4 | E98: 241126 | G98: E8E1 | H98: beta | I98: 67744 | J98: D:\Data\Document\ProductsLibrary\C线产品资料库\BK2007\beta\BK2007_0.11.4.241126_beta\US\BK2007_US_0.11.4.241126_E8E1_beta_Encrypt.bin
A99: BK2007_US_0.11.4.241126_EF36_beta_Open.bin | B99: BK2007 | C99: US | D99: 0.11.4 | E99: 241126 | G99: EF36 | H99: beta | I99: 67724 | J99: D:\Data\Document\ProductsLibrary\C线产品资料库\BK2007\beta\BK2007_0.11.4.241126_beta\US\BK2007_US_0.11.4.241126_EF36_beta_Open.bin
A100: BK2007_DE_0.11.4.241126_E98C_release_Encrypt.bin | B100: BK2007 | C100: DE | D100: 0.11.4 | E100: 241126 | F100: =DATE(2000+LEFT(E100,2), MID(E100,3,2), RIGHT(E100,2)) -> 45622 | G100: E98C | H100: release | I100: 67744 | J100: D:\Data\Document\ProductsLibrary\C线产品资料库\BK2007\固件\release\BK2007_0.11.4.241126_release\DE\BK2007_DE_0.11.4.241126_E98C_release_Encrypt.bin
A101: BK2007_DE_0.11.4.241126_EFE1_release_Open.bin | B101: BK2007 | C101: DE | D101: 0.11.4 | E101: 241126 | F101: =DATE(2000+LEFT(E101,2), MID(E101,3,2), RIGHT(E101,2)) -> 45622 | G101: EFE1 | H101: release | I101: 67724 | J101: D:\Data\Document\ProductsLibrary\C线产品资料库\BK2007\固件\release\BK2007_0.11.4.241126_release\DE\BK2007_DE_0.11.4.241126_EFE1_release_Open.bin
A102: BK2007_UK_0.11.4.241126_E9A5_release_Encrypt.bin | B102: BK2007 | C102: UK | D102: 0.11.4 | E102: 241126 | F102: =DATE(2000+LEFT(E102,2), MID(E102,3,2), RIGHT(E102,2)) -> 45622 | G102: E9A5 | H102: release | I102: 67744 | J102: D:\Data\Document\ProductsLibrary\C线产品资料库\BK2007\固件\release\BK2007_0.11.4.241126_release\UK\BK2007_UK_0.11.4.241126_E9A5_release_Encrypt.bin
A103: BK2007_UK_0.11.4.241126_EFFA_release_Open.bin | B103: BK2007 | C103: UK | D103: 0.11.4 | E103: 241126 | F103: =DATE(2000+LEFT(E103,2), MID(E103,3,2), RIGHT(E103,2)) -> 45622 | G103: EFFA | H103: release | I103: 67724 | J103: D:\Data\Document\ProductsLibrary\C线产品资料库\BK2007\固件\release\BK2007_0.11.4.241126_release\UK\BK2007_UK_0.11.4.241126_EFFA_release_Open.bin
A104: BK2007_US_0.11.4.241126_E8E1_release_Encrypt.bin | B104: BK2007 | C104: US | D104: 0.11.4 | E104: 241126 | F104: =DATE(2000+LEFT(E104,2), MID(E104,3,2), RIGHT(E104,2)) -> 45622 | G104: E8E1 | H104: release | I104: 67744 | J104: D:\Data\Document\ProductsLibrary\C线产品资料库\BK2007\固件\release\BK2007_0.11.4.241126_release\US\BK2007_US_0.11.4.241126_E8E1_release_Encrypt.bin
A105: BK2007_US_0.11.4.241126_EF36_release_Open.bin | B105: BK2007 | C105: US | D105: 0.11.4 | E105: 241126 | F105: =DATE(2000+LEFT(E105,2), MID(E105,3,2), RIGHT(E105,2)) -> 45622 | G105: EF36 | H105: release | I105: 67724 | J105: D:\Data\Document\ProductsLibrary\C线产品资料库\BK2007\固件\release\BK2007_0.11.4.241126_release\US\BK2007_US_0.11.4.241126_EF36_release_Open.bin
A106: KB06007_DE_0.0.3.241126_9E02_beta_Open.bin | B106: KB06007 | C106: DE | D106: 0.0.3 | E106: 241126 | G106: 9E02 | H106: beta | I106: 67128 | J106: D:\Data\Document\ProductsLibrary\C线产品资料库\KB06007\固件\beta\KB06007_0.0.3.241126_beta\DE\KB06007_DE_0.0.3.241126_9E02_beta_Open.bin
A107: KB06007_DE_0.0.3.241126_9F94_beta_Encrypt.bin | B107: KB06007 | C107: DE | D107: 0.0.3 | E107: 241126 | G107: 9F94 | H107: beta | I107: 67148 | J107: D:\Data\Document\ProductsLibrary\C线产品资料库\KB06007\固件\beta\KB06007_0.0.3.241126_beta\DE\KB06007_DE_0.0.3.241126_9F94_beta_Encrypt.bin
A108: KB06007_DE_0.0.4.241127_9C1E_beta_Open.bin | B108: KB06007 | C108: DE | D108: 0.0.4 | E108: 241127 | G108: 9C1E | H108: beta | I108: 67116 | J108: D:\Data\Document\ProductsLibrary\C线产品资料库\KB06007\固件\beta\KB06007_0.0.4.241127_beta\DE\KB06007_DE_0.0.4.241127_9C1E_beta_Open.bin
A109: KB06007_DE_0.0.4.241127_9FBC_beta_Encrypt.bin | B109: KB06007 | C109: DE | D109: 0.0.4 | E109: 241127 | G109: 9FBC | H109: beta | I109: 67136 | J109: D:\Data\Document\ProductsLibrary\C线产品资料库\KB06007\固件\beta\KB06007_0.0.4.241127_beta\DE\KB06007_DE_0.0.4.241127_9FBC_beta_Encrypt.bin
A110: KB01105_DE_0.0.7.241128_ABB5_beta_Open.bin | B110: KB01105 | C110: DE | D110: 0.0.7 | E110: 241128 | G110: ABB5 | H110: beta | I110: 82948 | J110: D:\Data\Document\ProductsLibrary\C线产品资料库\KB01105\固件\beta\KB01105_0.0.7.241128_beta\DE\KB01105_DE_0.0.7.241128_ABB5_beta_Open.bin
A111: KB01105_UK_0.0.7.241128_A228_beta_Open.bin | B111: KB01105 | C111: UK | D111: 0.0.7 | E111: 241128 | G111: A228 | H111: beta | I111: 82896 | J111: D:\Data\Document\ProductsLibrary\C线产品资料库\KB01105\固件\beta\KB01105_0.0.7.241128_beta\UK\KB01105_UK_0.0.7.241128_A228_beta_Open.bin
A112: KB01105_US_0.0.7.241128_8CAC_beta_Open.bin | B112: KB01105 | C112: US | D112: 0.0.7 | E112: 241128 | G112: 8CAC | H112: beta | I112: 82676 | J112: D:\Data\Document\ProductsLibrary\C线产品资料库\KB01105\固件\beta\KB01105_0.0.7.241128_beta\US\KB01105_US_0.0.7.241128_8CAC_beta_Open.bin
A113: KB01105_DE_0.0.8.241129_A417_beta_Open.bin | B113: KB01105 | C113: DE | D113: 0.0.8 | E113: 241129 | G113: A417 | H113: beta | I113: 82940 | J113: D:\Data\Document\ProductsLibrary\C线产品资料库\KB01105\固件\beta\KB01105_0.0.8.241129_beta\DE\KB01105_DE_0.0.8.241129_A417_beta_Open.bin
A114: KB01105_UK_0.0.8.241129_A580_beta_Open.bin | B114: KB01105 | C114: UK | D114: 0.0.8 | E114: 241129 | G114: A580 | H114: beta | I114: 82888 | J114: D:\Data\Document\ProductsLibrary\C线产品资料库\KB01105\固件\beta\KB01105_0.0.8.241129_beta\UK\KB01105_UK_0.0.8.241129_A580_beta_Open.bin
A115: KB01105_US_0.0.8.241129_87AB_beta_Open.bin | B115: KB01105 | C115: US | D115: 0.0.8 | E115: 241129 | G115: 87AB | H115: beta | I115: 82668 | J115: D:\Data\Document\ProductsLibrary\C线产品资料库\KB01105\固件\beta\KB01105_0.0.8.241129_beta\US\KB01105_US_0.0.8.241129_87AB_beta_Open.bin
A116: KB01105_DE_0.0.8.241129_A417_release_Open.bin | B116: KB01105 | C116: DE | D116: 0.0.8 | E116: 241129 | F116: =DATE(2000+LEFT(E116,2), MID(E116,3,2), RIGHT(E116,2)) -> 45625 | G116: A417 | H116: release | I116: 82940 | J116: D:\Data\Document\ProductsLibrary\C线产品资料库\KB01105\固件\release\KB01105_0.0.8.241129_release\DE\KB01105_DE_0.0.8.241129_A417_release_Open.bin
A117: KB01105_UK_0.0.8.241129_A580_release_Open.bin | B117: KB01105 | C117: UK | D117: 0.0.8 | E117: 241129 | F117: =DATE(2000+LEFT(E117,2), MID(E117,3,2), RIGHT(E117,2)) -> 45625 | G117: A580 | H117: release | I117: 82888 | J117: D:\Data\Document\ProductsLibrary\C线产品资料库\KB01105\固件\release\KB01105_0.0.8.241129_release\UK\KB01105_UK_0.0.8.241129_A580_release_Open.bin
A118: KB01105_US_0.0.8.241129_87AB_release_Open.bin | B118: KB01105 | C118: US | D118: 0.0.8 | E118: 241129 | F118: =DATE(2000+LEFT(E118,2), MID(E118,3,2), RIGHT(E118,2)) -> 45625 | G118: 87AB | H118: release | I118: 82668 | J118: D:\Data\Document\ProductsLibrary\C线产品资料库\KB01105\固件\release\KB01105_0.0.8.241129_release\US\KB01105_US_0.0.8.241129_87AB_release_Open.bin
A119: KB06007_DE_0.0.5.241129_AE64_beta_Open.bin | B119: KB06007 | C119: DE | D119: 0.0.5 | E119: 241129 | G119: AE64 | H119: beta | I119: 67172 | J119: D:\Data\Document\ProductsLibrary\C线产品资料库\KB06007\固件\beta\KB06007_0.0.5.241129_beta\DE\KB06007_DE_0.0.5.241129_AE64_beta_Open.bin
A120: KB06007_DE_0.0.5.241129_B1FB_beta_Encrypt.bin | B120: KB06007 | C120: DE | D120: 0.0.5 | E120: 241129 | G120: B1FB | H120: beta | I120: 67192 | J120: D:\Data\Document\ProductsLibrary\C线产品资料库\KB06007\固件\beta\KB06007_0.0.5.241129_beta\DE\KB06007_DE_0.0.5.241129_B1FB_beta_Encrypt.bin
A121: KB04122_DE_0.0.13.241203_99AA_beta_Encrypt.bin | B121: KB04122 | C121: DE | D121: 0.0.13 | E121: 241203 | G121: 99AA | H121: beta | I121: 81140 | J121: D:\Data\Document\ProductsLibrary\C线产品资料库\KB04122\固件\beta\KB04122_0.0.13.241203_beta\DE\KB04122_DE_0.0.13.241203_99AA_beta_Encrypt.bin
A122: KB04122_DE_0.0.13.241203_AEE1_beta_Open.bin | B122: KB04122 | C122: DE | D122: 0.0.13 | E122: 241203 | G122: AEE1 | H122: beta | I122: 81116 | J122: D:\Data\Document\ProductsLibrary\C线产品资料库\KB04122\固件\beta\KB04122_0.0.13.241203_beta\DE\KB04122_DE_0.0.13.241203_AEE1_beta_Open.bin
A123: KB04122_JP_0.0.13.241203_95E8_beta_Open.bin | B123: KB04122 | C123: JP | D123: 0.0.13 | E123: 241203 | G123: 95E8 | H123: beta | I123: 80940 | J123: D:\Data\Document\ProductsLibrary\C线产品资料库\KB04122\固件\beta\KB04122_0.0.13.241203_beta\JP\KB04122_JP_0.0.13.241203_95E8_beta_Open.bin
A124: KB04122_JP_0.0.13.241203_A786_beta_Encrypt.bin | B124: KB04122 | C124: JP | D124: 0.0.13 | E124: 241203 | G124: A786 | H124: beta | I124: 80972 | J124: D:\Data\Document\ProductsLibrary\C线产品资料库\KB04122\固件\beta\KB04122_0.0.13.241203_beta\JP\KB04122_JP_0.0.13.241203_A786_beta_Encrypt.bin
A125: KB04122_UK_0.0.13.241203_99B1_beta_Encrypt.bin | B125: KB04122 | C125: UK | D125: 0.0.13 | E125: 241203 | G125: 99B1 | H125: beta | I125: 81140 | J125: D:\Data\Document\ProductsLibrary\C线产品资料库\KB04122\固件\beta\KB04122_0.0.13.241203_beta\UK\KB04122_UK_0.0.13.241203_99B1_beta_Encrypt.bin
A126: KB04122_UK_0.0.13.241203_AEE8_beta_Open.bin | B126: KB04122 | C126: UK | D126: 0.0.13 | E126: 241203 | G126: AEE8 | H126: beta | I126: 81116 | J126: D:\Data\Document\ProductsLibrary\C线产品资料库\KB04122\固件\beta\KB04122_0.0.13.241203_beta\UK\KB04122_UK_0.0.13.241203_AEE8_beta_Open.bin
A127: KB04122_US_0.0.13.241203_95F9_beta_Open.bin | B127: KB04122 | C127: US | D127: 0.0.13 | E127: 241203 | G127: 95F9 | H127: beta | I127: 80940 | J127: D:\Data\Document\ProductsLibrary\C线产品资料库\KB04122\固件\beta\KB04122_0.0.13.241203_beta\US\KB04122_US_0.0.13.241203_95F9_beta_Open.bin
A128: KB04122_US_0.0.13.241203_A797_beta_Encrypt.bin | B128: KB04122 | C128: US | D128: 0.0.13 | E128: 241203 | G128: A797 | H128: beta | I128: 80972 | J128: D:\Data\Document\ProductsLibrary\C线产品资料库\KB04122\固件\beta\KB04122_0.0.13.241203_beta\US\KB04122_US_0.0.13.241203_A797_beta_Encrypt.bin
A129: KB06103_DE_0.1.30.241203_10D6_release_Encrypt.bin | B129: KB06103 | C129: DE | D129: 0.1.30 | E129: 241203 | F129: =DATE(2000+LEFT(E129,2), MID(E129,3,2), RIGHT(E129,2)) -> 45629 | G129: 10D6 | H129: release | I129: 79036 | J129: D:\Data\Document\ProductsLibrary\C线产品资料库\KB05114\KB06103\固件\release\KB06103_0.1.30.241203_release\DE\KB06103_DE_0.1.30.241203_10D6_release_Encrypt.bin
A130: KB06103_DE_0.1.30.241203_3313_release_Open.bin | B130: KB06103 | C130: DE | D130: 0.1.30 | E130: 241203 | F130: =DATE(2000+LEFT(E130,2), MID(E130,3,2), RIGHT(E130,2)) -> 45629 | G130: 3313 | H130: release | I130: 79016 | J130: D:\Data\Document\ProductsLibrary\C线产品资料库\KB05114\KB06103\固件\release\KB06103_0.1.30.241203_release\DE\KB06103_DE_0.1.30.241203_3313_release_Open.bin
A131: KB06103_US_0.1.30.241203_DDD5_release_Encrypt.bin | B131: KB06103 | C131: US | D131: 0.1.30 | E131: 241203 | F131: =DATE(2000+LEFT(E131,2), MID(E131,3,2), RIGHT(E131,2)) -> 45629 | G131: DDD5 | H131: release | I131: 78776 | J131: D:\Data\Document\ProductsLibrary\C线产品资料库\KB05114\KB06103\固件\release\KB06103_0.1.30.241203_release\US\KB06103_US_0.1.30.241203_DDD5_release_Encrypt.bin
...

Sheet SelfDeveloped
A1: 序号 | B1: 项目名称 | C1: 是否已release | D1: 最新release时间 | E1: 当前最新进展 | F1: 运用自研单片机 | G1: 硬件是否自研 | H1: 触控板软件 | I1: 配置tag | J1: 配置tag功能 | K1: 蓝牙轮询 | L1: 触控预设手势 | M1: 充电加快 | N1: 按压唤醒 | O1: 全域压感 | P1: 按键开机 | Q1: 电量管理优化 | R1: 触控优化 | S1: OTA | T1: 触控与按键同时使用
A2: 1 | B2: KB05113 | C2: 是 | D2: 45450 | E2: 已生产 | H2: 1.0.0 | I2: 0 | J2: 0 | K2: 0 | L2: 0 | M2: 0 | N2: 0 | O2: 0 | P2: 0 | Q2: 0 | R2: 0 | S2: 1 | T2: 0
A3: 2 | B3: MS06006 | C3: 是 | D3: 45637 | E3: 已生产 | H3: 无 | I3: 0 | J3: 0 | K3: 0 | L3: 无 | M3: 0 | N3: 0 | O3: 0 | P3: 0 | Q3: 0 | R3: 无 | S3: 1 | T3: 无
A4: 3 | B4: KB01104 | C4: 是 | D4: 45639 | E4: 已生产 | H4: 1.0.0 | I4: 0 | J4: 0 | K4: 0 | L4: 0 | M4: 0 | N4: 0 | O4: 0 | P4: 0 | Q4: 0 | R4: 0 | S4: 1 | T4: 0
A5: 4 | B5: KB06007 | C5: 是 | D5: 45659 | E5: 已生产 | H5: 无 | I5: 0 | J5: 0 | K5: 1 | L5: 无 | M5: 0 | N5: 0 | O5: 0 | P5: 0 | Q5: 0 | R5: 无 | S5: 1 | T5: 无
A6: 5 | B6: KB06006 | C6: 是 | D6: 45659 | E6: 已生产 | H6: 无 | I6: 0 | J6: 0 | K6: 1 | L6: 无 | M6: 0 | N6: 0 | O6: 0 | P6: 0 | Q6: 0 | R6: 无 | S6: 1 | T6: 无
A7: 6 | B7: KB01103 | C7: 是 | D7: 45666 | E7: 已生产 | H7: 1.0.0 | I7: 0 | J7: 0 | K7: 1 | L7: 0 | M7: 0 | N7: 0 | O7: 0 | P7: 0 | Q7: 0 | R7: 0 | S7: 1 | T7: 0
A8: 7 | B8: KB06103 | C8: 是 | D8: 45696 | E8: 已生产 | H8: 1.0.0 | I8: 0 | J8: 0 | K8: 1 | L8: 0 | M8: 0 | N8: 0 | O8: 0 | P8: 0 | Q8: 0 | R8: 0 | S8: 1 | T8: 0
A9: 8 | B9: KB02027 | C9: 是 | D9: 45783 | E9: 已生产 | H9: 1.0.0 | I9: 0 | J9: 0 | K9: 0 | L9: 0 | M9: 0 | N9: 0 | O9: 0 | P9: 0 | Q9: 0 | R9: 0 | S9: 1 | T9: 部分修饰键放开
A10: 9 | B10: KB02028 | C10: 是 | D10: 45783 | E10: 已生产 | H10: 1.0.0 | I10: 0 | J10: 0 | K10: 0 | L10: 0 | M10: 0 | N10: 0 | O10: 0 | P10: 0 | Q10: 0 | R10: 0 | S10: 1 | T10: 部分修饰键放开
A11: 10 | B11: KB602 | C11: 是 | D11: 45798 | E11: 已生产 | H11: 无 | I11: 1 | J11: 自定义按键，调节休眠时间 | K11: 1 | L11: 无 | M11: 0 | N11: 0 | O11: 0 | P11: 0 | Q11: 1 | R11: 无 | S11: 1 | T11: 无
A12: 11 | B12: KB01105 | C12: 是 | D12: 45805 | E12: 已生产 | H12: 1.0.0 | I12: 0 | J12: 0 | K12: 1 | L12: 0 | M12: 0 | N12: 0 | O12: 0 | P12: 0 | Q12: 0 | R12: 0 | S12: 1 | T12: 部分修饰键放开
A13: 12 | B13: KB04122 | C13: 是 | D13: 45807 | E13: 已生产 | H13: 2.0.0 | I13: 1 | J13: 触控预设手势 | K13: 1 | L13: 1 | M13: 0 | N13: 0 | O13: 0 | P13: 0 | Q13: 0 | R13: 1 | S13: 1 | T13: 按下时防误触
A14: 13 | B14: KB05114 | C14: 是 | D14: 45813 | E14: 已生产 | H14: 1.0.0 | I14: 0 | J14: 0 | K14: 1 | L14: 0 | M14: 0 | N14: 0 | O14: 0 | P14: 0 | Q14: 0 | R14: 0 | S14: 1 | T14: 部分修饰键放开
A15: 14 | B15: KB002 | C15: 是 | D15: 45853 | E15: 已生产 | H15: 1.0.0 | I15: 0 | J15: 0 | K15: 1 | L15: 0 | M15: 0 | N15: 0 | O15: 0 | P15: 0 | Q15: 0 | R15: 0 | S15: 1 | T15: 部分修饰键放开
A16: 15 | B16: KB04111 | C16: 是 | D16: 45856 | E16: 已生产 | H16: 1.0.0 | I16: 0 | J16: 0 | K16: 1 | L16: 1 | M16: 0 | N16: 0 | O16: 0 | P16: 0 | Q16: 0 | R16: 0 | S16: 1 | T16: 部分修饰键放开
A17: 16 | B17: KB04112 | C17: 是 | D17: 45856 | E17: 已生产 | H17: 1.0.0 | I17: 0 | J17: 0 | K17: 1 | L17: 1 | M17: 0 | N17: 0 | O17: 0 | P17: 0 | Q17: 0 | R17: 0 | S17: 1 | T17: 部分修饰键放开
A18: 17 | B18: KB09119 | C18: 是 | D18: 45895 | E18: 已生产 | H18: 1.0.0 | I18: 0 | J18: 0 | K18: 1 | L18: 1 | M18: 0 | N18: 0 | O18: 0 | P18: 0 | Q18: 0 | R18: 0 | S18: 1 | T18: 部分修饰键放开
A19: 18 | B19: KB06101 | C19: 是 | D19: 45903 | E19: 已生产 | H19: 1.0.0 | I19: 1 | J19: 自定义按键，调节休眠时间，触控板开关，触控预设手势 | K19: 1 | L19: 1 | M19: 1 | N19: 0 | O19: 0 | P19: 0 | Q19: 0 | R19: 0 | S19: 1 | T19: 0
A20: 19 | B20: BK2007-13 | C20: 是 | D20: 45904 | E20: 已生产 | H20: 无 | I20: 0 | J20: 0 | K20: 1 | L20: 无 | M20: 0 | N20: 无 | O20: 无 | P20: 0 | Q20: 0 | R20: 无 | S20: 1 | T20: 无
A21: 19 | B21: BK2007 | C21: 是 | D21: 45904 | E21: 已生产 | H21: 无 | I21: 0 | J21: 0 | K21: 1 | L21: 无 | M21: 0 | N21: 无 | O21: 无 | P21: 0 | Q21: 0 | R21: 无 | S21: 1 | T21: 无
A22: 20 | B22: KB403_10A | C22: 是 | D22: 45911 | E22: 已生产 | F22: 是 | G22: 是 | H22: 1.0.0 | I22: 1 | J22: 自定义按键、触控板开关、触控预设手势、休眠时间调整 | K22: 1 | L22: 1 | M22: 1 | N22: 1 | O22: 0 | P22: 1 | Q22: 1 | R22: 0 | S22: 1 | T22: 部分修饰键放开
A23: 21 | B23: KB04122-13A | C23: 是 | D23: 45929 | E23: 已生产 | F23: 最新版是 | G23: 最新版是 | H23: 1.0.0 | I23: 1 | J23: 自定义按键、触控板开关、背光颜色时间调整、触控预设手势、休眠时间调整 | K23: 1 | L23: 1 | M23: 1 | N23: 1 | O23: 0 | P23: 1 | Q23: 0 | R23: 0 | S23: 1 | T23: 部分修饰键放开
A24: 22 | B24: KB903-11A | C24: 是 | D24: 45961 | E24: 已生产 | H24: 1.0.0 | I24: 1 | J24: 自定义按键、触控板开关、背光颜色时间调整、触控预设手势、休眠时间调整 | K24: 1 | L24: 1 | M24: 1 | N24: 1 | O24: 0 | P24: 1 | Q24: 0 | R24: 0 | S24: 1 | T24: 按下时防误触
A25: 23 | B25: KB903-13A | C25: 是 | D25: 45961 | E25: 已生产 | H25: 1.0.0 | I25: 1 | J25: 自定义按键、触控板开关、背光颜色时间调整、触控预设手势、休眠时间调整 | K25: 1 | L25: 1 | M25: 1 | N25: 1 | O25: 0 | P25: 1 | Q25: 0 | R25: 0 | S25: 1 | T25: 按下时防误触
A26: 24 | B26: KB04122_RGB | C26: 是 | D26: 46003 | E26: 已验收 | H26: 1.0.0 | I26: 1 | J26: 触控板开关、背光颜色时间调整、触控预设手势、休眠时间调整 | K26: 1 | L26: 1 | M26: 0 | N26: 0 | O26: 0 | P26: 0 | Q26: 0 | R26: 0 | S26: 1 | T26: 部分修饰键放开
A27: 25 | B27: KB405 | C27: 是 | D27: 46009 | E27: 已验收 | F27: 是 | G27: 是 | H27: 2.0.0 | I27: 0 | J27: 0 | K27: 1 | L27: 1 | M27: 1 | N27: 1 | O27: 0 | P27: 1 | Q27: 0 | R27: 1 | S27: 1 | T27: 部分修饰键放开
A28: 26 | B28: KB105 | C28: 否 | E28: 验收中 | F28: 是 | G28: 是 | H28: 1.0.0 | I28: 1 | J28: 自定义按键、触控板开关、背光颜色时间调整、触控预设手势、休眠时间调整 | K28: 1 | L28: 1 | M28: 1 | N28: 1 | O28: 0 | P28: 1 | Q28: 0 | R28: 0 | S28: 1 | T28: 按下时防误触
A29: 27 | B29: KB604 | C29: 否 | E29: 开发中 | H29: 1.0.0 | I29: 1 | J29: 自定义按键、触控板开关、触控预设手势、休眠时间调整 | K29: 1 | L29: 1 | M29: 0 | N29: 0 | O29: 0 | P29: 0 | Q29: 1 | R29: 0 | S29: 1 | T29: 按下时防误触
A30: 28 | B30: KB403X | C30: 否 | E30: 验收中 | F30: 是 | G30: 是 | H30: 1.0.0 | I30: 1 | J30: 自定义按键、触控板开关、背光颜色时间调整、触控预设手势、休眠时间调整 | K30: 1 | L30: 1 | M30: 1 | N30: 0 | O30: 1 | P30: 1 | Q30: 0 | R30: 0 | S30: 1 | T30: 按下时防误触
A31: 29 | B31: KB06007 UK | C31: 否 | E31: 开发中 | H31: 无 | I31: 1 | J31: 自定义按键、休眠时间调整 | K31: 1 | L31: 无 | M31: 0 | N31: 0 | O31: 无 | P31: 0 | Q31: 0 | R31: 0 | S31: 1 | T31: 无
A32: 30 | B32: KB06007 Mac | C32: 否 | E32: 开发中 | H32: 无 | I32: 1 | J32: 自定义按键、休眠时间调整 | K32: 1 | L32: 无 | M32: 0 | N32: 0 | O32: 无 | P32: 0 | Q32: 0 | R32: 0 | S32: 1 | T32: 无
A33: 31 | B33: KB107 | C33: 否 | E33: 验收中 | H33: 无 | I33: 1 | J33: 自定义按键、休眠时间调整 | K33: 1 | L33: 无 | M33: 0 | N33: 0 | O33: 无 | P33: 0 | Q33: 1 | R33: 0 | S33: 1 | T33: 无
A34: 32 | B34: T001 | C34: 否 | E34: 开发中 | F34: 是 | G34: 是 | S34: 1
B35: kb02017
B36: KB04111-11
B37: KB09119-11
B38: KB09119-10
B39: KB04002
B40: KB04122-11
B41: KB09118
B42: MS02002
B43: KB19117
B44: KB403-10
B45: KB09117
B46: BK2007-RGB

Sheet Sales
A1: 序号 | B1: 产品 | C1: 是否固件自研 | D1: 产品名称 | E1: 品类 | F1: 销售额 | G1: 同比销售额 | H1: 同比销售额差 | I1: 销量 | J1: 同比销量 | K1: 同比销量差 | L1: 月平均成交价 | M1: 同比月平均成交价 | N1: 销售额占比 | O1: 毛利润额 | P1: 同比毛利润额 | Q1: 同比毛利润差 | R1: 毛利润率 | S1: 同比毛利润率 | T1: 利润额占比 | U1: 站内广告费用 | V1: 站内广告费用占比
A2: 1 | B2: =IFERROR(LEFT(D2, SEARCH("_", D2) - 1), D2) -> KB01104 | C2: =IF(COUNTIF(SelfDeveloped!$B:$B, B2)>0, 1, 0) -> 1 | D2: KB01104_gray | E2: Tablet Keyboard | F2: 179074.6 | G2: 45369.6 | H2: 133705 | I2: 4010 | J2: 893 | K2: 3117 | L2: 44.7 | M2: 50.8 | N2: 0.00% | O2: 10444.4 | P2: 3774.3 | Q2: 6670.1 | R2: 5.80% | S2: 8.20% | T2: 0.00% | U2: 21512.8 | V2: 12.00%
A3: 2 | B3: =IFERROR(LEFT(D3, SEARCH("_", D3) - 1), D3) -> KB04122 | C3: =IF(COUNTIF(SelfDeveloped!$B:$B, B3)>0, 1, 0) -> 1 | D3: KB04122_graphite | E3: Tablet Keyboard | F3: 65094.5 | G3: 0 | H3: 65094.5 | I3: 1174 | J3: 0 | K3: 1174 | L3: 55.4 | M3: 0 | N3: 0.00% | O3: -894.1 | P3: 0 | Q3: -894.1 | R3: -25.90% | S3: 0.00% | T3: 0.00% | U3: 1636.2 | V3: 47.40%
A4: 3 | B4: =IFERROR(LEFT(D4, SEARCH("_", D4) - 1), D4) -> KB04122-13A | C4: =IF(COUNTIF(SelfDeveloped!$B:$B, B4)>0, 1, 0) -> 1 | D4: KB04122-13A_gray | E4: Tablet Keyboard | F4: 693.4 | G4: 0 | H4: 693.4 | I4: 13 | J4: 0 | K4: 13 | L4: 53.3 | M4: 0 | N4: 0.00% | O4: -414.3 | P4: 0 | Q4: -414.3 | R4: -385.40% | S4: 0.00% | T4: 0.00% | U4: 281.1 | V4: 261.50%
A5: 4 | B5: =IFERROR(LEFT(D5, SEARCH("_", D5) - 1), D5) -> KB02009 | C5: =IF(COUNTIF(SelfDeveloped!$B:$B, B5)>0, 1, 0) -> 0 | D5: KB02009_black | E5: Tablet Keyboard | F5: 43462.3 | G5: 190807.9 | H5: -147345.6 | I5: 1142 | J5: 5258 | K5: -4116 | L5: 38.1 | M5: 36.3 | N5: 0.00% | O5: 2690.5 | P5: 1563.9 | Q5: 1126.6 | R5: 6.10% | S5: 0.80% | T5: 0.00% | U5: 1621.3 | V5: 3.70%
A6: 5 | B6: =IFERROR(LEFT(D6, SEARCH("_", D6) - 1), D6) -> BK2006 | C6: =IF(COUNTIF(SelfDeveloped!$B:$B, B6)>0, 1, 0) -> 0 | D6: BK2006_black | E6: Tablet Keyboard | F6: 430891.4 | G6: 801234.7 | H6: -370343.3 | I6: 13330 | J6: 23968 | K6: -10638 | L6: 32.3 | M6: 33.4 | N6: 0.00% | O6: 43377.2 | P6: 83052.5 | Q6: -39675.3 | R6: 10.10% | S6: 10.50% | T6: 0.00% | U6: 27303.4 | V6: 6.40%
A7: 6 | B7: =IFERROR(LEFT(D7, SEARCH("_", D7) - 1), D7) -> MS02001 | C7: =IF(COUNTIF(SelfDeveloped!$B:$B, B7)>0, 1, 0) -> 0 | D7: MS02001_black | E7: Mouse | F7: 31798 | G7: 81663.5 | H7: -49865.5 | I7: 2141 | J7: 5617 | K7: -3476 | L7: 14.9 | M7: 14.5 | N7: 0.00% | O7: 4493.4 | P7: 10374.8 | Q7: -5881.4 | R7: 14.10% | S7: 12.70% | T7: 0.00% | U7: 0 | V7: 0.00%
A8: 7 | B8: =IFERROR(LEFT(D8, SEARCH("_", D8) - 1), D8) -> KB602 | C8: =IF(COUNTIF(SelfDeveloped!$B:$B, B8)>0, 1, 0) -> 1 | D8: KB602_black | E8: Tablet Keyboard | F8: 56219.8 | G8: 0 | H8: 56219.8 | I8: 1576 | J8: 0 | K8: 1576 | L8: 35.7 | M8: 0 | N8: 0.00% | O8: 672.2 | P8: 0 | Q8: 672.2 | R8: 1.20% | S8: 0.00% | T8: 0.00% | U8: 10319.4 | V8: 18.90%
A9: 8 | B9: =IFERROR(LEFT(D9, SEARCH("_", D9) - 1), D9) -> KB02017 | C9: =IF(COUNTIF(SelfDeveloped!$B:$B, B9)>0, 1, 0) -> 1 | D9: KB02017_black | E9: Tablet Keyboard | F9: 37.2 | G9: 0 | H9: 37.2 | I9: 1 | J9: 0 | K9: 1 | L9: 37.2 | M9: 0 | N9: 0.00% | O9: 4 | P9: 0 | Q9: 4 | R9: 10.80% | S9: 0.00% | T9: 0.00% | U9: 0 | V9: 0.00%
A10: 9 | B10: =IFERROR(LEFT(D10, SEARCH("_", D10) - 1), D10) -> BK2007 | C10: =IF(COUNTIF(SelfDeveloped!$B:$B, B10)>0, 1, 0) -> 1 | D10: BK2007_purple | E10: Tablet Keyboard | F10: 184652.2 | G10: 169179 | H10: 15473.2 | I10: 5323 | J10: 4544 | K10: 779 | L10: 34.7 | M10: 37.2 | N10: 0.00% | O10: 26057 | P10: 19440.1 | Q10: 6616.9 | R10: 14.00% | S10: 11.20% | T10: 0.00% | U10: 0 | V10: 0.00%
A11: 10 | B11: =IFERROR(LEFT(D11, SEARCH("_", D11) - 1), D11) -> KB04111-11 | C11: =IF(COUNTIF(SelfDeveloped!$B:$B, B11)>0, 1, 0) -> 1 | D11: KB04111-11_gray | E11: Tablet Keyboard | F11: 36842 | G11: 7747.4 | H11: 29094.6 | I11: 769 | J11: 121 | K11: 648 | L11: 47.9 | M11: 64 | N11: 0.00% | O11: -3584.3 | P11: -279.5 | Q11: -3304.8 | R11: -9.70% | S11: -3.60% | T11: 0.00% | U11: 1528.8 | V11: 4.10%
A12: 11 | B12: =IFERROR(LEFT(D12, SEARCH("_", D12) - 1), D12) -> KB09119-11 | C12: =IF(COUNTIF(SelfDeveloped!$B:$B, B12)>0, 1, 0) -> 1 | D12: KB09119-11_black | E12: Tablet Keyboard | F12: 8869.7 | G12: 0 | H12: 8869.7 | I12: 213 | J12: 0 | K12: 213 | L12: 41.6 | M12: 0 | N12: 0.00% | O12: -1987 | P12: 0 | Q12: -1987 | R12: -22.50% | S12: 0.00% | T12: 0.00% | U12: 47.2 | V12: 0.50%
A13: 12 | B13: =IFERROR(LEFT(D13, SEARCH("_", D13) - 1), D13) -> KB09119-10 | C13: =IF(COUNTIF(SelfDeveloped!$B:$B, B13)>0, 1, 0) -> 1 | D13: KB09119-10_white | E13: Tablet Keyboard | F13: 232820.8 | G13: 0 | H13: 232820.8 | I13: 3323 | J13: 0 | K13: 3323 | L13: 70.1 | M13: 0 | N13: 0.00% | O13: 45685 | P13: 0 | Q13: 45685 | R13: 20.20% | S13: 0.00% | T13: 0.00% | U13: 5219.3 | V13: 2.30%
... A79: 79 | B79: =IFERROR(LEFT(D79, SEARCH("_", D79) - 1), D79) -> KB06001 | C79: =IF(COUNTIF(SelfDeveloped!$B:$B, B79)>0, 1, 0) -> 0 | D79: KB06001_white | E79: Tablet Keyboard | F79: 31010.2 | G79: 0 | H79: 31010.2 | I79: 1468 | J79: 0 | K79: 1468 | L79: 21.1 | M79: 0 | N79: 0.00% | O79: -3533.7 | P79: 0 | Q79: -3533.7 | R79: -11.50% | S79: 0.00% | T79: 0.00% | U79: 4018.9 | V79: 13.00%

Sheet 自研固件占比透视表
A1: 行标签 | B1: 最大值项:固件自研 | C1: 求和项:销售额 | D1: 求和项:销量
A2: BK2006 | B2: 0 | C2: 430891.4 | D2: 13330
A3: BK2007 | B3: 1 | C3: 1958533.3 | D3: 55922
A4: BK2007-13 | B4: 1 | C4: 454203.7 | D4: 7256
A5: BK2007-RGB | B5: 1 | C5: 211956.7 | D5: 5081
A6: BK2009 | B6: 0 | C6: 28.1 | D6: 11
A7: KB002 | B7: 1 | C7: 590447.5 | D7: 14745
A8: KB003-11A | B8: 0 | C8: 72303.9 | D8: 2123
A9: KB004 | B9: 0 | C9: 56257.2 | D9: 1378
A10: KB01003 | B10: 0 | C10: 105066.2 | D10: 5700
A11: KB01103 | B11: 1 | C11: 52864.9 | D11: 1706
A12: KB01104 | B12: 1 | C12: 179074.6 | D12: 4010
A13: KB01105 | B13: 1 | C13: 294581.2 | D13: 8637
... A50: 总计 | B50: 1 | C50: 20075566 | D50: 416324

Sheet 自研固件占比
A1: 行标签 | B1: 最大值项:固件自研 | C1: 求和项:销售额 | D1: 求和项:销量
A2: BK2006 | B2: 0 | C2: 430891.4 | D2: 13330
A3: BK2007 | B3: 1 | C3: 1958533.3 | D3: 55922
A4: BK2007-13 | B4: 1 | C4: 454203.7 | D4: 7256
A5: BK2007-RGB | B5: 1 | C5: 211956.7 | D5: 5081
A6: BK2009 | B6: 0 | C6: 28.1 | D6: 11
A7: KB002 | B7: 1 | C7: 590447.5 | D7: 14745
A8: KB003-11A | B8: 0 | C8: 72303.9 | D8: 2123
A9: KB004 | B9: 0 | C9: 56257.2 | D9: 1378
A10: KB01003 | B10: 0 | C10: 105066.2 | D10: 5700
A11: KB01103 | B11: 1 | C11: 52864.9 | D11: 1706
A12: KB01104 | B12: 1 | C12: 179074.6 | D12: 4010
A13: KB01105 | B13: 1 | C13: 294581.2 | D13: 8637
... A48: MS02002 | B48: 1 | C48: 1354.6 | D48: 97
A49: 总计 | C49: =SUM(C2:C48) -> 20070768 | D49: =SUM(D2:D48) -> 416015
A50: 自研固件数量 | B50: 32
A51: 总计数 | B51: 47
C52: =SUMIFS(C2:C48, B2:B48, 1) -> 18000541 | D52: =SUMIFS(D2:D48, B2:B48, 1) -> 367927
A53: 自研固件占比 | B53: =B50/B51 -> 0.68085106
A54: 自研固件销售额占比 | B54: =D52/D49 -> 0.88440801
A55: 自研固件销量占比 | B55: =C52/C49 -> 0.89685363
C1048576: =SUM(C2:C1048575) -> 58142077

Sheet 固件销量表
A1: 序号 | B1: 产品 | C1: 固件自研 | D1: 销售额 | E1: 销量 | H1: 1
A2: 1 | B2: KB01104 | C2: 1 | D2: 179074.6 | E2: 4010
A3: 2 | B3: KB04122 | C3: 1 | D3: 65094.5 | E3: 1174
A4: 3 | B4: KB04122-13A | C4: 1 | D4: 693.4 | E4: 13
A5: 4 | B5: KB02009 | C5: 0 | D5: 43462.3 | E5: 1142
A6: 5 | B6: BK2006 | C6: 0 | D6: 430891.4 | E6: 13330
A7: 6 | B7: MS02001 | C7: 0 | D7: 31798 | E7: 2141
A8: 7 | B8: KB602 | C8: 1 | D8: 56219.8 | E8: 1576
A9: 8 | B9: KB02017 | C9: 1 | D9: 37.2 | E9: 1
A10: 9 | B10: BK2007 | C10: 1 | D10: 184652.2 | E10: 5323
A11: 10 | B11: KB04111-11 | C11: 1 | D11: 36842 | E11: 769
A12: 11 | B12: KB09119-11 | C12: 1 | D12: 8869.7 | E12: 213
A13: 12 | B13: KB09119-10 | C13: 1 | D13: 232820.8 | E13: 3323
... A79: 79 | B79: KB06001 | C79: 0 | D79: 31010.2 | E79: 1468
